{
    "boxShadow": "none",
    "mobileBottomRow": 50.599999999999994,
    "widgetName": "IconButton1",
    "onClick": "{{navigateTo('Reviews', {}, 'SAME_WINDOW');}}",
    "buttonColor": "{{appsmith.theme.colors.primaryColor}}",
    "displayName": "Icon button",
    "iconSVG": "/static/media/icon.b08054586989b185a0801e9a34f8ad49.svg",
    "searchTags": [
        "click",
        "submit"
    ],
    "topRow": 52.400000000000006,
    "bottomRow": 56.400000000000006,
    "parentRowSpace": 10,
    "type": "ICON_BUTTON_WIDGET",
    "hideCard": false,
    "mobileRightColumn": 12.075471698113208,
    "animateLoading": true,
    "parentColumnSpace": 11.34375,
    "dynamicTriggerPathList": [{"key": "onClick"}],
    "leftColumn": 0,
    "dynamicBindingPathList": [
        {"key": "buttonColor"},
        {"key": "borderRadius"}
    ],
    "isDisabled": false,
    "key": "1zaenw6txe",
    "isDeprecated": false,
    "rightColumn": 3.1449631449631448,
    "iconName": "arrow-left",
    "widgetId": "0lbpnz47qv",
    "minWidth": 50,
    "isVisible": true,
    "version": 1,
    "parentId": "0",
    "tags": ["Buttons"],
    "renderMode": "CANVAS",
    "isLoading": false,
    "mobileTopRow": 46.599999999999994,
    "responsiveBehavior": "hug",
    "borderRadius": "{{appsmith.theme.borderRadius.appBorderRadius}}",
    "mobileLeftColumn": 0,
    "buttonVariant": "PRIMARY",
    "alignment": "start"
}